aiyc1v1/__init__.py
aiyc1v1/__version__.py
aiyc1v1/aiycwordcloud.py
aiyc1v1/simplenlp.py
aiycsnlp/__init__.py
aiycsnlp/__version__.py
aiycsnlp/aiycsnlp.py
aiycsnlp/aiycwordcloud.py
aiycsnlp/wordcloud.py
tests/__init__.py
tests/aiycsnlp-Tester.py
aiycsnlp-0.0.14.dist-info/LICENSE
aiycsnlp-0.0.14.dist-info/METADATA
aiycsnlp-0.0.14.dist-info/WHEEL
aiycsnlp-0.0.14.dist-info/top_level.txt
aiycsnlp-0.0.14.dist-info/RECORD
