Metadata-Version: 2.1
Name: aiycsnlp
Version: 0.0.14
Summary: AIYC SimpleNLP
Home-page: https://github.com/AndersonHJB/aiyc-snlp
Author: Bornforthis
Author-email: bornforthis@bornforthis.com
License: MIT
Classifier: License :: OSI Approved :: MIT License
Classifier: Programming Language :: Python
Classifier: Programming Language :: Python :: 3
Classifier: Programming Language :: Python :: 3.6
Classifier: Programming Language :: Python :: Implementation :: CPython
Classifier: Programming Language :: Python :: Implementation :: PyPy
Requires-Python: >=3.6.0
License-File: LICENSE
Requires-Dist: pyecharts
